{
"autoplayBgm":false,"autoplayBgs":false,"battleback1Name":"","battleback2Name":"","bgm":{"name":"","pan":0,"pitch":100,"volume":90},"bgs":{"name":"","pan":0,"pitch":100,"volume":90},"disableDashing":false,"displayName":"","encounterList":[],"encounterStep":30,"height":7,"note":"","parallaxLoopX":false,"parallaxLoopY":false,"parallaxName":"","parallaxShow":true,"parallaxSx":0,"parallaxSy":0,"scrollType":0,"specifyBattleback":false,"tilesetId":10,"width":8,
"data":[1573,1573,1573,1573,1573,1573,1573,1573,1573,1573,1573,1573,1573,1573,1573,1573,1573,1573,1573,1573,1573,1573,1573,1573,1573,1573,1573,1573,1573,1573,1573,1573,1573,1573,1573,1573,1573,1573,1573,1573,1573,1573,1573,1573,1573,1573,1573,1573,1573,1573,1573,1549,1549,1573,1573,1573,258,259,260,259,260,259,260,261,266,268,267,268,267,268,267,269,274,276,275,276,276,276,275,277,0,0,0,0,0,0,0,0,0,0,0,0,0,0,0,0,0,0,0,0,0,0,0,0,0,0,0,0,0,0,0,0,0,352,352,352,352,352,352,0,0,360,360,360,360,360,360,0,0,276,275,0,0,276,275,0,0,0,0,0,0,0,0,0,274,0,0,0,0,0,0,277,0,0,0,0,0,0,0,0,0,0,0,0,0,0,0,0,0,0,0,0,0,0,0,0,0,0,0,0,0,0,0,0,258,0,0,362,363,0,0,261,266,0,0,0,0,0,0,269,258,0,0,0,0,0,0,261,266,0,0,0,0,0,0,269,274,0,0,0,0,0,0,277,0,0,0,0,0,0,0,0,0,0,0,0,0,0,0,0,0,0,0,0,0,0,0,0,0,0,0,0,0,0,0,0,0,0,0,0,0,0,0,0,0,0,0,0,0,0,0,0,0,0,0,0,0,0,0,0,0,0,0,0,0,0,0,0,0,0,0,0,0,0,0,0,0,0,0,0,0,0,0,0,0,0,0,0,0,0,0,0,0,0,0,0,0,0,0,0,0,0,0,0,0,0,0,0,0,0,0,1,1,0,0,0],
"events":[
null,
{"id":1,"name":"florinette","note":"","pages":[{"conditions":{"actorId":1,"actorValid":false,"itemId":1,"itemValid":false,"selfSwitchCh":"A","selfSwitchValid":false,"switch1Id":1,"switch1Valid":false,"switch2Id":1,"switch2Valid":false,"variableId":1,"variableValid":false,"variableValue":0},"directionFix":false,"image":{"tileId":0,"characterName":"HGSS Pokes 001","direction":2,"pattern":0,"characterIndex":4},"list":[{"code":0,"indent":0,"parameters":[]}],"moveFrequency":3,"moveRoute":{"list":[{"code":0,"parameters":[]}],"repeat":true,"skippable":false,"wait":false},"moveSpeed":3,"moveType":0,"priorityType":1,"stepAnime":false,"through":true,"trigger":0,"walkAnime":true},{"conditions":{"actorId":1,"actorValid":false,"itemId":1,"itemValid":false,"selfSwitchCh":"A","selfSwitchValid":false,"switch1Id":63,"switch1Valid":true,"switch2Id":1,"switch2Valid":false,"variableId":1,"variableValid":false,"variableValue":0},"directionFix":false,"image":{"characterIndex":0,"characterName":"","direction":2,"pattern":0,"tileId":0},"list":[{"code":0,"indent":0,"parameters":[]}],"moveFrequency":3,"moveRoute":{"list":[{"code":0,"parameters":[]}],"repeat":true,"skippable":false,"wait":false},"moveSpeed":3,"moveType":0,"priorityType":0,"stepAnime":false,"through":false,"trigger":0,"walkAnime":false},{"conditions":{"actorId":1,"actorValid":false,"itemId":1,"itemValid":false,"selfSwitchCh":"B","selfSwitchValid":false,"switch1Id":78,"switch1Valid":true,"switch2Id":1,"switch2Valid":false,"variableId":1,"variableValid":false,"variableValue":0},"directionFix":true,"image":{"tileId":0,"characterName":"HGSS Pokes 001","direction":4,"pattern":0,"characterIndex":4},"list":[{"code":111,"indent":0,"parameters":[0,97,0]},{"code":205,"indent":1,"parameters":[1,{"list":[{"code":36,"indent":null},{"code":16,"indent":null},{"code":0}],"repeat":false,"skippable":false,"wait":false}]},{"code":505,"indent":1,"parameters":[{"code":36,"indent":null}]},{"code":505,"indent":1,"parameters":[{"code":16,"indent":null}]},{"code":250,"indent":1,"parameters":[{"name":"_pixel-sound-effect-5-103221","volume":90,"pitch":150,"pan":0}]},{"code":213,"indent":1,"parameters":[1,1,false]},{"code":101,"indent":1,"parameters":["1-8",2,0,2,"Florinette"]},{"code":401,"indent":1,"parameters":["Que se passe-t-il les enfants ? Vous avez l'air"]},{"code":401,"indent":1,"parameters":["d'avoir quelque chose de très important à me"]},{"code":401,"indent":1,"parameters":["dire"]},{"code":101,"indent":1,"parameters":["1-8",0,0,2,"Bulbi"]},{"code":401,"indent":1,"parameters":["Mamie ! \\N[12] vient de débloquer une nouvelle"]},{"code":401,"indent":1,"parameters":["compétence, une capacité innée !"]},{"code":101,"indent":1,"parameters":["1-8",2,0,2,"Florinette"]},{"code":401,"indent":1,"parameters":["Oh ! Intéressant ! Donc même les Nyxoro ont"]},{"code":401,"indent":1,"parameters":["des capacités innées. Puis-je la voir ?"]},{"code":101,"indent":1,"parameters":["",0,1,1,""]},{"code":401,"indent":1,"parameters":[""]},{"code":401,"indent":1,"parameters":["          Vous vous concentrez de toute vos forces"]},{"code":230,"indent":1,"parameters":[60]},{"code":212,"indent":1,"parameters":[-1,55,true]},{"code":205,"indent":1,"parameters":[1,{"list":[{"code":44,"parameters":[{"name":"_pixel-jump-319167","volume":90,"pitch":100,"pan":0}],"indent":null},{"code":14,"parameters":[0,0],"indent":null},{"code":44,"parameters":[{"name":"_pixel-jump-319167","volume":90,"pitch":100,"pan":0}],"indent":null},{"code":14,"parameters":[0,0],"indent":null},{"code":0}],"repeat":false,"skippable":false,"wait":false}]},{"code":505,"indent":1,"parameters":[{"code":44,"parameters":[{"name":"_pixel-jump-319167","volume":90,"pitch":100,"pan":0}],"indent":null}]},{"code":505,"indent":1,"parameters":[{"code":14,"parameters":[0,0],"indent":null}]},{"code":505,"indent":1,"parameters":[{"code":44,"parameters":[{"name":"_pixel-jump-319167","volume":90,"pitch":100,"pan":0}],"indent":null}]},{"code":505,"indent":1,"parameters":[{"code":14,"parameters":[0,0],"indent":null}]},{"code":213,"indent":1,"parameters":[1,1,false]},{"code":101,"indent":1,"parameters":["1-8",2,0,2,"Florinette"]},{"code":401,"indent":1,"parameters":["Je n'ai jamais vu une telle aura. C'est très "]},{"code":401,"indent":1,"parameters":["impréssionnant !"]},{"code":101,"indent":1,"parameters":["1-8",2,0,2,"Florinette"]},{"code":401,"indent":1,"parameters":["Une capacité innée puise dans tes réserves de"]},{"code":401,"indent":1,"parameters":["\\C[23]puissance personnelle (PP)\\C[0]. C'est un"]},{"code":401,"indent":1,"parameters":["signe d'une grande combativité. Tous les poké-"]},{"code":401,"indent":1,"parameters":["-mons n'arrivent pas forcément à accèder à leur"]},{"code":101,"indent":1,"parameters":["1-8",2,0,2,"Florinette"]},{"code":401,"indent":1,"parameters":["PP. Mais chaque famille de pokémon possède ses"]},{"code":401,"indent":1,"parameters":["propres capacités innées. Il me tarde de "]},{"code":401,"indent":1,"parameters":["découvrir tout ce que tu nous réserve encore !"]},{"code":213,"indent":1,"parameters":[-1,2,true]},{"code":101,"indent":1,"parameters":["1-8",0,0,2,"Bulbi"]},{"code":401,"indent":1,"parameters":["Et moi mamie ?"]},{"code":101,"indent":1,"parameters":["1-8",2,0,2,"Florinette"]},{"code":401,"indent":1,"parameters":["C'est vraiment quelque chose d'exceptionnel"]},{"code":401,"indent":1,"parameters":["que \\N[12] ait débloqué sa puissance "]},{"code":401,"indent":1,"parameters":["personnelle aussi jeune, mais ne t'en fais pas "]},{"code":401,"indent":1,"parameters":["mon petit bulbi, mon sang coule dans tes veines"]},{"code":101,"indent":1,"parameters":["1-8",2,0,2,"Florinette"]},{"code":401,"indent":1,"parameters":["toi aussi tu finiras par y accèder, mais plus "]},{"code":401,"indent":1,"parameters":["tard"]},{"code":101,"indent":1,"parameters":["1-8",0,0,2,"Bulbi"]},{"code":401,"indent":1,"parameters":["Trop cool ! T'as entendu \\N[12] ?! Moi aussi"]},{"code":401,"indent":1,"parameters":["je vais devenir aussi fort que toi héhéhé"]},{"code":101,"indent":1,"parameters":["1-8",2,0,2,""]},{"code":401,"indent":1,"parameters":["Si ça ne vous dérange pas, je vais aller faire"]},{"code":401,"indent":1,"parameters":["une petite sieste."]},{"code":121,"indent":1,"parameters":[97,97,1]},{"code":0,"indent":1,"parameters":[]},{"code":411,"indent":0,"parameters":[]},{"code":213,"indent":1,"parameters":[1,10,true]},{"code":0,"indent":1,"parameters":[]},{"code":412,"indent":0,"parameters":[]},{"code":0,"indent":0,"parameters":[]}],"moveFrequency":3,"moveRoute":{"list":[{"code":0,"parameters":[]}],"repeat":true,"skippable":false,"wait":false},"moveSpeed":3,"moveType":0,"priorityType":1,"stepAnime":false,"through":true,"trigger":0,"walkAnime":true}],"x":4,"y":2},
{"id":2,"name":"bulbi","note":"","pages":[{"conditions":{"actorId":1,"actorValid":false,"itemId":1,"itemValid":false,"selfSwitchCh":"A","selfSwitchValid":false,"switch1Id":1,"switch1Valid":false,"switch2Id":1,"switch2Valid":false,"variableId":1,"variableValid":false,"variableValue":0},"directionFix":false,"image":{"tileId":0,"characterName":"HGSS Pokes 001","direction":6,"pattern":1,"characterIndex":0},"list":[{"code":0,"indent":0,"parameters":[]}],"moveFrequency":3,"moveRoute":{"list":[{"code":0,"parameters":[]}],"repeat":true,"skippable":false,"wait":false},"moveSpeed":3,"moveType":0,"priorityType":1,"stepAnime":true,"through":false,"trigger":0,"walkAnime":true},{"conditions":{"actorId":1,"actorValid":false,"itemId":1,"itemValid":false,"selfSwitchCh":"A","selfSwitchValid":false,"switch1Id":63,"switch1Valid":true,"switch2Id":1,"switch2Valid":false,"variableId":1,"variableValid":false,"variableValue":0},"directionFix":false,"image":{"characterIndex":0,"characterName":"","direction":2,"pattern":0,"tileId":0},"list":[{"code":0,"indent":0,"parameters":[]}],"moveFrequency":3,"moveRoute":{"list":[{"code":0,"parameters":[]}],"repeat":true,"skippable":false,"wait":false},"moveSpeed":3,"moveType":0,"priorityType":0,"stepAnime":false,"through":false,"trigger":0,"walkAnime":true}],"x":3,"y":3},
{"id":3,"name":"bulbi post scout","note":"","pages":[{"conditions":{"actorId":1,"actorValid":false,"itemId":1,"itemValid":false,"selfSwitchCh":"A","selfSwitchValid":false,"switch1Id":74,"switch1Valid":true,"switch2Id":1,"switch2Valid":false,"variableId":1,"variableValid":false,"variableValue":0},"directionFix":false,"image":{"tileId":0,"characterName":"HGSS Pokes 001","direction":8,"pattern":0,"characterIndex":0},"list":[{"code":0,"indent":0,"parameters":[]}],"moveFrequency":3,"moveRoute":{"list":[{"code":0,"parameters":[]}],"repeat":true,"skippable":false,"wait":false},"moveSpeed":3,"moveType":0,"priorityType":1,"stepAnime":false,"through":false,"trigger":0,"walkAnime":true},{"conditions":{"actorId":1,"actorValid":false,"itemId":1,"itemValid":false,"selfSwitchCh":"A","selfSwitchValid":false,"switch1Id":76,"switch1Valid":true,"switch2Id":1,"switch2Valid":false,"variableId":1,"variableValid":false,"variableValue":0},"directionFix":false,"image":{"tileId":0,"characterName":"","direction":8,"pattern":0,"characterIndex":0},"list":[{"code":0,"indent":0,"parameters":[]}],"moveFrequency":3,"moveRoute":{"list":[{"code":0,"parameters":[]}],"repeat":true,"skippable":false,"wait":false},"moveSpeed":3,"moveType":0,"priorityType":0,"stepAnime":false,"through":false,"trigger":0,"walkAnime":true}],"x":3,"y":5},
{"id":4,"name":"opening scene","note":"","pages":[{"conditions":{"actorId":1,"actorValid":false,"itemId":1,"itemValid":false,"selfSwitchCh":"A","selfSwitchValid":false,"switch1Id":1,"switch1Valid":false,"switch2Id":1,"switch2Valid":false,"variableId":1,"variableValid":false,"variableValue":0},"directionFix":false,"image":{"characterIndex":0,"characterName":"","direction":2,"pattern":0,"tileId":0},"list":[{"code":213,"indent":0,"parameters":[2,1,false]},{"code":205,"indent":0,"parameters":[2,{"list":[{"code":14,"parameters":[0,0],"indent":null},{"code":44,"parameters":[{"name":"pixel-jump-319167","volume":90,"pitch":100,"pan":0}],"indent":0},{"code":14,"parameters":[0,0],"indent":null},{"code":44,"parameters":[{"name":"pixel-jump-319167","volume":90,"pitch":100,"pan":0}],"indent":null},{"code":0}],"repeat":false,"skippable":false,"wait":true}]},{"code":505,"indent":0,"parameters":[{"code":14,"parameters":[0,0],"indent":null}]},{"code":505,"indent":0,"parameters":[{"code":44,"parameters":[{"name":"pixel-jump-319167","volume":90,"pitch":100,"pan":0}],"indent":0}]},{"code":505,"indent":0,"parameters":[{"code":14,"parameters":[0,0],"indent":null}]},{"code":505,"indent":0,"parameters":[{"code":44,"parameters":[{"name":"pixel-jump-319167","volume":90,"pitch":100,"pan":0}],"indent":null}]},{"code":101,"indent":0,"parameters":["1-8",0,0,2,"Bulbi"]},{"code":401,"indent":0,"parameters":[""]},{"code":401,"indent":0,"parameters":["Mamie! C'est lui le pokémon dont je t'ai parlé!"]},{"code":101,"indent":0,"parameters":["1-8",2,0,2,""]},{"code":401,"indent":0,"parameters":["Je t'ai déjà dit de pas m'appeler comme ça"]},{"code":401,"indent":0,"parameters":["quand nous ne sommes pas seuls !"]},{"code":101,"indent":0,"parameters":["1-8",0,0,2,"Bulbi"]},{"code":401,"indent":0,"parameters":["Oui désolé mamie... Euh je veux dire madame"]},{"code":401,"indent":0,"parameters":["le maire de Vertemousse."]},{"code":101,"indent":0,"parameters":["1-8",2,0,2,""]},{"code":401,"indent":0,"parameters":["C'est bon, n'en fait pas trop non plus.."]},{"code":401,"indent":0,"parameters":["Bon laisse moi accueillir cet ami dont tu m'as "]},{"code":401,"indent":0,"parameters":["parlé."]},{"code":101,"indent":0,"parameters":["nyxoro_face",0,1,2,""]},{"code":401,"indent":0,"parameters":[""]},{"code":401,"indent":0,"parameters":["Ami ? "]},{"code":205,"indent":0,"parameters":[2,{"list":[{"code":16,"indent":null},{"code":32,"indent":null},{"code":34,"indent":null},{"code":0}],"repeat":false,"skippable":false,"wait":false}]},{"code":505,"indent":0,"parameters":[{"code":16,"indent":null}]},{"code":505,"indent":0,"parameters":[{"code":32,"indent":null}]},{"code":505,"indent":0,"parameters":[{"code":34,"indent":null}]},{"code":205,"indent":0,"parameters":[1,{"list":[{"code":1,"indent":null},{"code":1,"indent":null},{"code":15,"parameters":[120],"indent":null},{"code":0}],"repeat":false,"skippable":false,"wait":true}]},{"code":505,"indent":0,"parameters":[{"code":1,"indent":null}]},{"code":505,"indent":0,"parameters":[{"code":1,"indent":null}]},{"code":505,"indent":0,"parameters":[{"code":15,"parameters":[120],"indent":null}]},{"code":213,"indent":0,"parameters":[1,1,true]},{"code":205,"indent":0,"parameters":[1,{"list":[{"code":14,"parameters":[0,0],"indent":null},{"code":44,"parameters":[{"name":"pixel-jump-319167","volume":90,"pitch":100,"pan":0}],"indent":0},{"code":14,"parameters":[0,0],"indent":null},{"code":44,"parameters":[{"name":"pixel-jump-319167","volume":90,"pitch":100,"pan":0}],"indent":null},{"code":0}],"repeat":false,"skippable":false,"wait":true}]},{"code":505,"indent":0,"parameters":[{"code":14,"parameters":[0,0],"indent":null}]},{"code":505,"indent":0,"parameters":[{"code":44,"parameters":[{"name":"pixel-jump-319167","volume":90,"pitch":100,"pan":0}],"indent":0}]},{"code":505,"indent":0,"parameters":[{"code":14,"parameters":[0,0],"indent":null}]},{"code":505,"indent":0,"parameters":[{"code":44,"parameters":[{"name":"pixel-jump-319167","volume":90,"pitch":100,"pan":0}],"indent":null}]},{"code":101,"indent":0,"parameters":["1-8",2,0,2,""]},{"code":401,"indent":0,"parameters":["Non c'est impossible..."]},{"code":205,"indent":0,"parameters":[1,{"list":[{"code":37,"indent":null},{"code":29,"parameters":[5],"indent":null},{"code":2,"indent":null},{"code":1,"indent":null},{"code":25,"indent":null},{"code":15,"parameters":[60],"indent":null},{"code":4,"indent":null},{"code":3,"indent":null},{"code":3,"indent":null},{"code":1,"indent":null},{"code":25,"indent":null},{"code":14,"parameters":[0,0],"indent":null},{"code":44,"parameters":[{"name":"pixel-jump-319167","volume":90,"pitch":100,"pan":0}],"indent":0},{"code":13,"indent":null},{"code":15,"parameters":[60],"indent":null},{"code":12,"indent":null},{"code":4,"indent":null},{"code":2,"indent":null},{"code":25,"indent":null},{"code":32,"indent":null},{"code":0}],"repeat":false,"skippable":false,"wait":true}]},{"code":505,"indent":0,"parameters":[{"code":37,"indent":null}]},{"code":505,"indent":0,"parameters":[{"code":29,"parameters":[5],"indent":null}]},{"code":505,"indent":0,"parameters":[{"code":2,"indent":null}]},{"code":505,"indent":0,"parameters":[{"code":1,"indent":null}]},{"code":505,"indent":0,"parameters":[{"code":25,"indent":null}]},{"code":505,"indent":0,"parameters":[{"code":15,"parameters":[60],"indent":null}]},{"code":505,"indent":0,"parameters":[{"code":4,"indent":null}]},{"code":505,"indent":0,"parameters":[{"code":3,"indent":null}]},{"code":505,"indent":0,"parameters":[{"code":3,"indent":null}]},{"code":505,"indent":0,"parameters":[{"code":1,"indent":null}]},{"code":505,"indent":0,"parameters":[{"code":25,"indent":null}]},{"code":505,"indent":0,"parameters":[{"code":14,"parameters":[0,0],"indent":null}]},{"code":505,"indent":0,"parameters":[{"code":44,"parameters":[{"name":"pixel-jump-319167","volume":90,"pitch":100,"pan":0}],"indent":0}]},{"code":505,"indent":0,"parameters":[{"code":13,"indent":null}]},{"code":505,"indent":0,"parameters":[{"code":15,"parameters":[60],"indent":null}]},{"code":505,"indent":0,"parameters":[{"code":12,"indent":null}]},{"code":505,"indent":0,"parameters":[{"code":4,"indent":null}]},{"code":505,"indent":0,"parameters":[{"code":2,"indent":null}]},{"code":505,"indent":0,"parameters":[{"code":25,"indent":null}]},{"code":505,"indent":0,"parameters":[{"code":32,"indent":null}]},{"code":101,"indent":0,"parameters":["1-8",2,0,2,""]},{"code":401,"indent":0,"parameters":["Ma vieillesse me joue des tours, "]},{"code":401,"indent":0,"parameters":["c'est impossible..."]},{"code":213,"indent":0,"parameters":[2,2,false]},{"code":101,"indent":0,"parameters":["1-8",0,0,2,"Bulbi"]},{"code":401,"indent":0,"parameters":["Qu'est-ce qu'il se passe mamie ?"]},{"code":401,"indent":0,"parameters":["Je ne t'ai jamais vu comme ça.."]},{"code":101,"indent":0,"parameters":["1-8",2,0,2,""]},{"code":401,"indent":0,"parameters":["Tu t'appelles \\P[1] c'est ça ?"]},{"code":101,"indent":0,"parameters":["nyxoro_face",0,0,2,""]},{"code":401,"indent":0,"parameters":[""]},{"code":401,"indent":0,"parameters":["Oui..."]},{"code":101,"indent":0,"parameters":["1-8",2,0,2,""]},{"code":401,"indent":0,"parameters":["Écoutes moi attentivement \\P[1]."]},{"code":401,"indent":0,"parameters":["Je ne suis pas encore sûre de moi, mais..."]},{"code":242,"indent":0,"parameters":[1]},{"code":250,"indent":0,"parameters":[{"name":"Explosion4","volume":90,"pitch":100,"pan":0}]},{"code":225,"indent":0,"parameters":[5,5,120,true]},{"code":108,"indent":0,"parameters":["jouer explosion ici si besoin"]},{"code":213,"indent":0,"parameters":[-1,1,false]},{"code":250,"indent":0,"parameters":[{"name":"_pixel-sound-effect-5-103221","volume":90,"pitch":150,"pan":0}]},{"code":213,"indent":0,"parameters":[1,1,false]},{"code":250,"indent":0,"parameters":[{"name":"_pixel-sound-effect-5-103221","volume":90,"pitch":150,"pan":0}]},{"code":213,"indent":0,"parameters":[2,1,false]},{"code":250,"indent":0,"parameters":[{"name":"_pixel-sound-effect-5-103221","volume":90,"pitch":150,"pan":0}]},{"code":101,"indent":0,"parameters":["1-8",0,0,2,"Bulbi"]},{"code":401,"indent":0,"parameters":[""]},{"code":401,"indent":0,"parameters":["Il se passe quelque chose dehors !"]},{"code":230,"indent":0,"parameters":[60]},{"code":205,"indent":0,"parameters":[2,{"list":[{"code":29,"parameters":[5],"indent":null},{"code":1,"indent":null},{"code":1,"indent":null},{"code":1,"indent":null},{"code":39,"indent":null},{"code":0}],"repeat":false,"skippable":false,"wait":true}]},{"code":505,"indent":0,"parameters":[{"code":29,"parameters":[5],"indent":null}]},{"code":505,"indent":0,"parameters":[{"code":1,"indent":null}]},{"code":505,"indent":0,"parameters":[{"code":1,"indent":null}]},{"code":505,"indent":0,"parameters":[{"code":1,"indent":null}]},{"code":505,"indent":0,"parameters":[{"code":39,"indent":null}]},{"code":250,"indent":0,"parameters":[{"name":"Switch1","volume":65,"pitch":50,"pan":0}]},{"code":101,"indent":0,"parameters":["1-8",2,0,2,""]},{"code":401,"indent":0,"parameters":["Vite, va voir ce qu'il se passe avec Bulbi, "]},{"code":401,"indent":0,"parameters":["j'arrive le temps de retrouver mes esprits."]},{"code":401,"indent":0,"parameters":["Nous reprendrons notre discussion plus tard"]},{"code":205,"indent":0,"parameters":[-1,{"list":[{"code":29,"parameters":[5],"indent":null},{"code":1,"indent":null},{"code":0}],"repeat":false,"skippable":false,"wait":true}]},{"code":505,"indent":0,"parameters":[{"code":29,"parameters":[5],"indent":null}]},{"code":505,"indent":0,"parameters":[{"code":1,"indent":null}]},{"code":242,"indent":0,"parameters":[1]},{"code":241,"indent":0,"parameters":[{"name":"02-Team-Flare-Appears_-","volume":60,"pitch":100,"pan":0}]},{"code":250,"indent":0,"parameters":[{"name":"Switch1","volume":65,"pitch":50,"pan":0}]},{"code":201,"indent":0,"parameters":[0,20,9,10,2,0]},{"code":222,"indent":0,"parameters":[]},{"code":121,"indent":0,"parameters":[63,63,0]},{"code":123,"indent":0,"parameters":["A",0]},{"code":0,"indent":0,"parameters":[]}],"moveFrequency":3,"moveRoute":{"list":[{"code":0,"parameters":[]}],"repeat":true,"skippable":false,"wait":false},"moveSpeed":3,"moveType":0,"priorityType":0,"stepAnime":false,"through":false,"trigger":3,"walkAnime":false},{"conditions":{"actorId":1,"actorValid":false,"itemId":1,"itemValid":false,"selfSwitchCh":"A","selfSwitchValid":true,"switch1Id":1,"switch1Valid":false,"switch2Id":1,"switch2Valid":false,"variableId":1,"variableValid":false,"variableValue":0},"directionFix":false,"image":{"characterIndex":0,"characterName":"","direction":2,"pattern":0,"tileId":0},"list":[{"code":0,"indent":0,"parameters":[]}],"moveFrequency":3,"moveRoute":{"list":[{"code":0,"parameters":[]}],"repeat":true,"skippable":false,"wait":false},"moveSpeed":3,"moveType":0,"priorityType":0,"stepAnime":false,"through":false,"trigger":0,"walkAnime":false}],"x":1,"y":0},
{"id":5,"name":"florinette post event","note":"","pages":[{"conditions":{"actorId":1,"actorValid":false,"itemId":1,"itemValid":false,"selfSwitchCh":"A","selfSwitchValid":false,"switch1Id":1,"switch1Valid":false,"switch2Id":1,"switch2Valid":false,"variableId":1,"variableValid":false,"variableValue":0},"directionFix":false,"image":{"characterIndex":0,"characterName":"","direction":2,"pattern":0,"tileId":0},"list":[{"code":0,"indent":0,"parameters":[]}],"moveFrequency":3,"moveRoute":{"list":[{"code":0,"parameters":[]}],"repeat":true,"skippable":false,"wait":false},"moveSpeed":3,"moveType":0,"priorityType":0,"stepAnime":false,"through":false,"trigger":0,"walkAnime":true},{"conditions":{"actorId":1,"actorValid":false,"itemId":1,"itemValid":false,"selfSwitchCh":"A","selfSwitchValid":false,"switch1Id":63,"switch1Valid":true,"switch2Id":1,"switch2Valid":false,"variableId":1,"variableValid":false,"variableValue":0},"directionFix":false,"image":{"tileId":0,"characterName":"HGSS Pokes 001","direction":2,"pattern":0,"characterIndex":4},"list":[{"code":0,"indent":0,"parameters":[]}],"moveFrequency":3,"moveRoute":{"list":[{"code":0,"parameters":[]}],"repeat":true,"skippable":false,"wait":false},"moveSpeed":3,"moveType":0,"priorityType":1,"stepAnime":false,"through":false,"trigger":0,"walkAnime":false},{"conditions":{"actorId":1,"actorValid":false,"itemId":1,"itemValid":false,"selfSwitchCh":"A","selfSwitchValid":false,"switch1Id":74,"switch1Valid":true,"switch2Id":1,"switch2Valid":false,"variableId":1,"variableValid":false,"variableValue":0},"directionFix":false,"image":{"characterIndex":0,"characterName":"","direction":2,"pattern":0,"tileId":0},"list":[{"code":0,"indent":0,"parameters":[]}],"moveFrequency":3,"moveRoute":{"list":[{"code":0,"parameters":[]}],"repeat":true,"skippable":false,"wait":false},"moveSpeed":3,"moveType":0,"priorityType":0,"stepAnime":false,"through":false,"trigger":0,"walkAnime":true}],"x":4,"y":4},
{"id":6,"name":"explosions","note":"","pages":[{"conditions":{"actorId":1,"actorValid":false,"itemId":1,"itemValid":false,"selfSwitchCh":"A","selfSwitchValid":false,"switch1Id":64,"switch1Valid":true,"switch2Id":1,"switch2Valid":false,"variableId":1,"variableValid":false,"variableValue":0},"directionFix":false,"image":{"characterIndex":0,"characterName":"","direction":2,"pattern":0,"tileId":0},"list":[{"code":212,"indent":0,"parameters":[6,69,false]},{"code":223,"indent":0,"parameters":[[34,-34,-68,170],60,false]},{"code":123,"indent":0,"parameters":["A",0]},{"code":0,"indent":0,"parameters":[]}],"moveFrequency":3,"moveRoute":{"list":[{"code":0,"parameters":[]}],"repeat":true,"skippable":false,"wait":false},"moveSpeed":3,"moveType":0,"priorityType":0,"stepAnime":false,"through":false,"trigger":4,"walkAnime":true},{"conditions":{"actorId":1,"actorValid":false,"itemId":1,"itemValid":false,"selfSwitchCh":"A","selfSwitchValid":true,"switch1Id":1,"switch1Valid":false,"switch2Id":1,"switch2Valid":false,"variableId":1,"variableValid":false,"variableValue":0},"directionFix":false,"image":{"characterIndex":0,"characterName":"","direction":2,"pattern":0,"tileId":0},"list":[{"code":0,"indent":0,"parameters":[]}],"moveFrequency":3,"moveRoute":{"list":[{"code":0,"parameters":[]}],"repeat":true,"skippable":false,"wait":false},"moveSpeed":3,"moveType":0,"priorityType":0,"stepAnime":false,"through":false,"trigger":0,"walkAnime":true}],"x":2,"y":0},
{"id":7,"name":"Florinette post scout","note":"","pages":[{"conditions":{"actorId":1,"actorValid":false,"itemId":1,"itemValid":false,"selfSwitchCh":"A","selfSwitchValid":false,"switch1Id":74,"switch1Valid":true,"switch2Id":1,"switch2Valid":false,"variableId":1,"variableValid":false,"variableValue":0},"directionFix":false,"image":{"tileId":0,"characterName":"HGSS Pokes 001","direction":2,"pattern":0,"characterIndex":4},"list":[{"code":111,"indent":0,"parameters":[0,97,0]},{"code":205,"indent":1,"parameters":[1,{"list":[{"code":36,"indent":null},{"code":16,"indent":null},{"code":0}],"repeat":false,"skippable":false,"wait":false}]},{"code":505,"indent":1,"parameters":[{"code":36,"indent":null}]},{"code":505,"indent":1,"parameters":[{"code":16,"indent":null}]},{"code":250,"indent":1,"parameters":[{"name":"_pixel-sound-effect-5-103221","volume":90,"pitch":150,"pan":0}]},{"code":213,"indent":1,"parameters":[1,1,false]},{"code":101,"indent":1,"parameters":["1-8",2,0,2,"Florinette"]},{"code":401,"indent":1,"parameters":["Que se passe-t-il les enfants ? Vous avez l'air"]},{"code":401,"indent":1,"parameters":["d'avoir quelque chose de très important à me"]},{"code":401,"indent":1,"parameters":["dire"]},{"code":101,"indent":1,"parameters":["1-8",0,0,2,"Bulbi"]},{"code":401,"indent":1,"parameters":["Mamie ! \\N[12] vient de débloquer une nouvelle"]},{"code":401,"indent":1,"parameters":["compétence, une capacité innée !"]},{"code":101,"indent":1,"parameters":["1-8",2,0,2,"Florinette"]},{"code":401,"indent":1,"parameters":["Oh ! Intéressant ! Donc même les Nyxoro ont"]},{"code":401,"indent":1,"parameters":["des capacités innées. Puis-je la voir ?"]},{"code":101,"indent":1,"parameters":["",0,1,1,""]},{"code":401,"indent":1,"parameters":[""]},{"code":401,"indent":1,"parameters":["          Vous vous concentrez de toute vos forces"]},{"code":230,"indent":1,"parameters":[60]},{"code":212,"indent":1,"parameters":[-1,55,true]},{"code":205,"indent":1,"parameters":[1,{"list":[{"code":44,"parameters":[{"name":"_pixel-jump-319167","volume":90,"pitch":100,"pan":0}],"indent":null},{"code":14,"parameters":[0,0],"indent":null},{"code":44,"parameters":[{"name":"_pixel-jump-319167","volume":90,"pitch":100,"pan":0}],"indent":null},{"code":14,"parameters":[0,0],"indent":null},{"code":0}],"repeat":false,"skippable":false,"wait":false}]},{"code":505,"indent":1,"parameters":[{"code":44,"parameters":[{"name":"_pixel-jump-319167","volume":90,"pitch":100,"pan":0}],"indent":null}]},{"code":505,"indent":1,"parameters":[{"code":14,"parameters":[0,0],"indent":null}]},{"code":505,"indent":1,"parameters":[{"code":44,"parameters":[{"name":"_pixel-jump-319167","volume":90,"pitch":100,"pan":0}],"indent":null}]},{"code":505,"indent":1,"parameters":[{"code":14,"parameters":[0,0],"indent":null}]},{"code":213,"indent":1,"parameters":[1,1,false]},{"code":101,"indent":1,"parameters":["1-8",2,0,2,"Florinette"]},{"code":401,"indent":1,"parameters":["Je n'ai jamais vu une telle aura. C'est très "]},{"code":401,"indent":1,"parameters":["impréssionnant !"]},{"code":101,"indent":1,"parameters":["1-8",2,0,2,"Florinette"]},{"code":401,"indent":1,"parameters":["Une capacité innée puise dans tes réserves de"]},{"code":401,"indent":1,"parameters":["\\C[23]puissance personnelle (PP)\\C[0]. C'est un"]},{"code":401,"indent":1,"parameters":["signe d'une grande combativité. Tous les poké-"]},{"code":401,"indent":1,"parameters":["-mons n'arrivent pas forcément à accèder à leur"]},{"code":101,"indent":1,"parameters":["1-8",2,0,2,"Florinette"]},{"code":401,"indent":1,"parameters":["PP. Mais chaque famille de pokémon possède ses"]},{"code":401,"indent":1,"parameters":["propres capacités innées. Il me tarde de "]},{"code":401,"indent":1,"parameters":["découvrir tout ce que tu nous réserve encore !"]},{"code":213,"indent":1,"parameters":[-1,2,true]},{"code":101,"indent":1,"parameters":["1-8",0,0,2,"Bulbi"]},{"code":401,"indent":1,"parameters":["Et moi mamie ?"]},{"code":101,"indent":1,"parameters":["1-8",2,0,2,"Florinette"]},{"code":401,"indent":1,"parameters":["C'est vraiment quelque chose d'exceptionnel"]},{"code":401,"indent":1,"parameters":["que \\N[12] ait débloqué sa puissance "]},{"code":401,"indent":1,"parameters":["personnelle aussi jeune, mais ne t'en fais pas "]},{"code":401,"indent":1,"parameters":["mon petit bulbi, mon sang coule dans tes veines"]},{"code":101,"indent":1,"parameters":["1-8",2,0,2,"Florinette"]},{"code":401,"indent":1,"parameters":["toi aussi tu finiras par y accèder, mais plus "]},{"code":401,"indent":1,"parameters":["tard"]},{"code":101,"indent":1,"parameters":["1-8",0,0,2,"Bulbi"]},{"code":401,"indent":1,"parameters":["Trop cool ! T'as entendu \\N[12] ?! Moi aussi"]},{"code":401,"indent":1,"parameters":["je vais devenir aussi fort que toi héhéhé"]},{"code":101,"indent":1,"parameters":["1-8",2,0,2,""]},{"code":401,"indent":1,"parameters":["Prenez soin de vous les petits et surtout"]},{"code":401,"indent":1,"parameters":["n'hésitez pas à revenir nous voir de temps en"]},{"code":401,"indent":1,"parameters":["temps !"]},{"code":121,"indent":1,"parameters":[97,97,1]},{"code":0,"indent":1,"parameters":[]},{"code":411,"indent":0,"parameters":[]},{"code":101,"indent":1,"parameters":["1-8",2,0,2,""]},{"code":401,"indent":1,"parameters":["Prenez soin de vous les petits et surtout"]},{"code":401,"indent":1,"parameters":["n'hésitez pas à revenir nous voir de temps en"]},{"code":401,"indent":1,"parameters":["temps !"]},{"code":0,"indent":1,"parameters":[]},{"code":412,"indent":0,"parameters":[]},{"code":123,"indent":0,"parameters":["A",0]},{"code":0,"indent":0,"parameters":[]}],"moveFrequency":3,"moveRoute":{"list":[{"code":0,"parameters":[]}],"repeat":true,"skippable":false,"wait":false},"moveSpeed":3,"moveType":0,"priorityType":1,"stepAnime":false,"through":false,"trigger":0,"walkAnime":true},{"conditions":{"actorId":1,"actorValid":false,"itemId":1,"itemValid":false,"selfSwitchCh":"A","selfSwitchValid":true,"switch1Id":74,"switch1Valid":false,"switch2Id":1,"switch2Valid":false,"variableId":1,"variableValid":false,"variableValue":0},"directionFix":false,"image":{"tileId":0,"characterName":"HGSS Pokes 001","direction":2,"pattern":0,"characterIndex":4},"list":[{"code":111,"indent":0,"parameters":[0,97,0]},{"code":205,"indent":1,"parameters":[1,{"list":[{"code":36,"indent":null},{"code":16,"indent":null},{"code":0}],"repeat":false,"skippable":false,"wait":false}]},{"code":505,"indent":1,"parameters":[{"code":36,"indent":null}]},{"code":505,"indent":1,"parameters":[{"code":16,"indent":null}]},{"code":250,"indent":1,"parameters":[{"name":"_pixel-sound-effect-5-103221","volume":90,"pitch":150,"pan":0}]},{"code":213,"indent":1,"parameters":[1,1,false]},{"code":101,"indent":1,"parameters":["1-8",2,0,2,"Florinette"]},{"code":401,"indent":1,"parameters":["Que se passe-t-il les enfants ? Vous avez l'air"]},{"code":401,"indent":1,"parameters":["d'avoir quelque chose de très important à me"]},{"code":401,"indent":1,"parameters":["dire"]},{"code":101,"indent":1,"parameters":["1-8",0,0,2,"Bulbi"]},{"code":401,"indent":1,"parameters":["Mamie ! \\N[12] vient de débloquer une nouvelle"]},{"code":401,"indent":1,"parameters":["compétence, une capacité innée !"]},{"code":101,"indent":1,"parameters":["1-8",2,0,2,"Florinette"]},{"code":401,"indent":1,"parameters":["Oh ! Intéressant ! Donc même les Nyxoro ont"]},{"code":401,"indent":1,"parameters":["des capacités innées. Puis-je la voir ?"]},{"code":101,"indent":1,"parameters":["",0,1,1,""]},{"code":401,"indent":1,"parameters":[""]},{"code":401,"indent":1,"parameters":["          Vous vous concentrez de toute vos forces"]},{"code":230,"indent":1,"parameters":[60]},{"code":212,"indent":1,"parameters":[-1,55,true]},{"code":205,"indent":1,"parameters":[1,{"list":[{"code":44,"parameters":[{"name":"_pixel-jump-319167","volume":90,"pitch":100,"pan":0}],"indent":null},{"code":14,"parameters":[0,0],"indent":null},{"code":44,"parameters":[{"name":"_pixel-jump-319167","volume":90,"pitch":100,"pan":0}],"indent":null},{"code":14,"parameters":[0,0],"indent":null},{"code":0}],"repeat":false,"skippable":false,"wait":false}]},{"code":505,"indent":1,"parameters":[{"code":44,"parameters":[{"name":"_pixel-jump-319167","volume":90,"pitch":100,"pan":0}],"indent":null}]},{"code":505,"indent":1,"parameters":[{"code":14,"parameters":[0,0],"indent":null}]},{"code":505,"indent":1,"parameters":[{"code":44,"parameters":[{"name":"_pixel-jump-319167","volume":90,"pitch":100,"pan":0}],"indent":null}]},{"code":505,"indent":1,"parameters":[{"code":14,"parameters":[0,0],"indent":null}]},{"code":213,"indent":1,"parameters":[1,1,false]},{"code":101,"indent":1,"parameters":["1-8",2,0,2,"Florinette"]},{"code":401,"indent":1,"parameters":["Je n'ai jamais vu une telle aura. C'est très "]},{"code":401,"indent":1,"parameters":["impréssionnant !"]},{"code":101,"indent":1,"parameters":["1-8",2,0,2,"Florinette"]},{"code":401,"indent":1,"parameters":["Une capacité innée puise dans tes réserves de"]},{"code":401,"indent":1,"parameters":["\\C[23]puissance personnelle (PP)\\C[0]. C'est un"]},{"code":401,"indent":1,"parameters":["signe d'une grande combativité. Tous les poké-"]},{"code":401,"indent":1,"parameters":["-mons n'arrivent pas forcément à accèder à leur"]},{"code":101,"indent":1,"parameters":["1-8",2,0,2,"Florinette"]},{"code":401,"indent":1,"parameters":["PP. Mais chaque famille de pokémon possède ses"]},{"code":401,"indent":1,"parameters":["propres capacités innées. Il me tarde de "]},{"code":401,"indent":1,"parameters":["découvrir tout ce que tu nous réserve encore !"]},{"code":213,"indent":1,"parameters":[-1,2,true]},{"code":101,"indent":1,"parameters":["1-8",0,0,2,"Bulbi"]},{"code":401,"indent":1,"parameters":["Et moi mamie ?"]},{"code":101,"indent":1,"parameters":["1-8",2,0,2,"Florinette"]},{"code":401,"indent":1,"parameters":["C'est vraiment quelque chose d'exceptionnel"]},{"code":401,"indent":1,"parameters":["que \\N[12] ait débloqué sa puissance "]},{"code":401,"indent":1,"parameters":["personnelle aussi jeune, mais ne t'en fais pas "]},{"code":401,"indent":1,"parameters":["mon petit bulbi, mon sang coule dans tes veines"]},{"code":101,"indent":1,"parameters":["1-8",2,0,2,"Florinette"]},{"code":401,"indent":1,"parameters":["toi aussi tu finiras par y accèder, mais plus "]},{"code":401,"indent":1,"parameters":["tard"]},{"code":101,"indent":1,"parameters":["1-8",0,0,2,"Bulbi"]},{"code":401,"indent":1,"parameters":["Trop cool ! T'as entendu \\N[12] ?! Moi aussi"]},{"code":401,"indent":1,"parameters":["je vais devenir aussi fort que toi héhéhé"]},{"code":101,"indent":1,"parameters":["1-8",2,0,2,""]},{"code":401,"indent":1,"parameters":["Si ça ne vous dérange pas, je vais aller faire"]},{"code":401,"indent":1,"parameters":["une petite sieste."]},{"code":121,"indent":1,"parameters":[97,97,1]},{"code":205,"indent":1,"parameters":[7,{"list":[{"code":37,"indent":null},{"code":4,"indent":null},{"code":17,"indent":null},{"code":0}],"repeat":false,"skippable":false,"wait":true}]},{"code":505,"indent":1,"parameters":[{"code":37,"indent":null}]},{"code":505,"indent":1,"parameters":[{"code":4,"indent":null}]},{"code":505,"indent":1,"parameters":[{"code":17,"indent":null}]},{"code":213,"indent":1,"parameters":[7,10,true]},{"code":121,"indent":1,"parameters":[78,78,0]},{"code":123,"indent":1,"parameters":["B",0]},{"code":0,"indent":1,"parameters":[]},{"code":411,"indent":0,"parameters":[]},{"code":101,"indent":1,"parameters":["1-8",2,0,2,""]},{"code":401,"indent":1,"parameters":["Si ça ne vous dérange pas, je vais aller faire"]},{"code":401,"indent":1,"parameters":["une petite sieste."]},{"code":205,"indent":1,"parameters":[7,{"list":[{"code":37,"indent":null},{"code":4,"indent":null},{"code":17,"indent":null},{"code":0}],"repeat":false,"skippable":false,"wait":true}]},{"code":505,"indent":1,"parameters":[{"code":37,"indent":null}]},{"code":505,"indent":1,"parameters":[{"code":4,"indent":null}]},{"code":505,"indent":1,"parameters":[{"code":17,"indent":null}]},{"code":213,"indent":1,"parameters":[7,10,true]},{"code":121,"indent":1,"parameters":[78,78,0]},{"code":123,"indent":1,"parameters":["B",0]},{"code":0,"indent":1,"parameters":[]},{"code":412,"indent":0,"parameters":[]},{"code":0,"indent":0,"parameters":[]}],"moveFrequency":3,"moveRoute":{"list":[{"code":0,"parameters":[]}],"repeat":true,"skippable":false,"wait":false},"moveSpeed":3,"moveType":0,"priorityType":1,"stepAnime":false,"through":false,"trigger":0,"walkAnime":true},{"conditions":{"actorId":1,"actorValid":false,"itemId":1,"itemValid":false,"selfSwitchCh":"B","selfSwitchValid":true,"switch1Id":74,"switch1Valid":false,"switch2Id":1,"switch2Valid":false,"variableId":1,"variableValid":false,"variableValue":0},"directionFix":true,"image":{"tileId":0,"characterName":"HGSS Pokes 001","direction":4,"pattern":0,"characterIndex":4},"list":[{"code":111,"indent":0,"parameters":[0,97,0]},{"code":205,"indent":1,"parameters":[1,{"list":[{"code":36,"indent":null},{"code":16,"indent":null},{"code":0}],"repeat":false,"skippable":false,"wait":false}]},{"code":505,"indent":1,"parameters":[{"code":36,"indent":null}]},{"code":505,"indent":1,"parameters":[{"code":16,"indent":null}]},{"code":250,"indent":1,"parameters":[{"name":"_pixel-sound-effect-5-103221","volume":90,"pitch":150,"pan":0}]},{"code":213,"indent":1,"parameters":[1,1,false]},{"code":101,"indent":1,"parameters":["1-8",2,0,2,"Florinette"]},{"code":401,"indent":1,"parameters":["Que se passe-t-il les enfants ? Vous avez l'air"]},{"code":401,"indent":1,"parameters":["d'avoir quelque chose de très important à me"]},{"code":401,"indent":1,"parameters":["dire"]},{"code":101,"indent":1,"parameters":["1-8",0,0,2,"Bulbi"]},{"code":401,"indent":1,"parameters":["Mamie ! \\N[12] vient de débloquer une nouvelle"]},{"code":401,"indent":1,"parameters":["compétence, une capacité innée !"]},{"code":101,"indent":1,"parameters":["1-8",2,0,2,"Florinette"]},{"code":401,"indent":1,"parameters":["Oh ! Intéressant ! Donc même les Nyxoro ont"]},{"code":401,"indent":1,"parameters":["des capacités innées. Puis-je la voir ?"]},{"code":101,"indent":1,"parameters":["",0,1,1,""]},{"code":401,"indent":1,"parameters":[""]},{"code":401,"indent":1,"parameters":["          Vous vous concentrez de toute vos forces"]},{"code":230,"indent":1,"parameters":[60]},{"code":212,"indent":1,"parameters":[-1,55,true]},{"code":205,"indent":1,"parameters":[1,{"list":[{"code":44,"parameters":[{"name":"_pixel-jump-319167","volume":90,"pitch":100,"pan":0}],"indent":null},{"code":14,"parameters":[0,0],"indent":null},{"code":44,"parameters":[{"name":"_pixel-jump-319167","volume":90,"pitch":100,"pan":0}],"indent":null},{"code":14,"parameters":[0,0],"indent":null},{"code":0}],"repeat":false,"skippable":false,"wait":false}]},{"code":505,"indent":1,"parameters":[{"code":44,"parameters":[{"name":"_pixel-jump-319167","volume":90,"pitch":100,"pan":0}],"indent":null}]},{"code":505,"indent":1,"parameters":[{"code":14,"parameters":[0,0],"indent":null}]},{"code":505,"indent":1,"parameters":[{"code":44,"parameters":[{"name":"_pixel-jump-319167","volume":90,"pitch":100,"pan":0}],"indent":null}]},{"code":505,"indent":1,"parameters":[{"code":14,"parameters":[0,0],"indent":null}]},{"code":213,"indent":1,"parameters":[1,1,false]},{"code":101,"indent":1,"parameters":["1-8",2,0,2,"Florinette"]},{"code":401,"indent":1,"parameters":["Je n'ai jamais vu une telle aura. C'est très "]},{"code":401,"indent":1,"parameters":["impréssionnant !"]},{"code":101,"indent":1,"parameters":["1-8",2,0,2,"Florinette"]},{"code":401,"indent":1,"parameters":["Une capacité innée puise dans tes réserves de"]},{"code":401,"indent":1,"parameters":["\\C[23]puissance personnelle (PP)\\C[0]. C'est un"]},{"code":401,"indent":1,"parameters":["signe d'une grande combativité. Tous les poké-"]},{"code":401,"indent":1,"parameters":["-mons n'arrivent pas forcément à accèder à leur"]},{"code":101,"indent":1,"parameters":["1-8",2,0,2,"Florinette"]},{"code":401,"indent":1,"parameters":["PP. Mais chaque famille de pokémon possède ses"]},{"code":401,"indent":1,"parameters":["propres capacités innées. Il me tarde de "]},{"code":401,"indent":1,"parameters":["découvrir tout ce que tu nous réserve encore !"]},{"code":213,"indent":1,"parameters":[-1,2,true]},{"code":101,"indent":1,"parameters":["1-8",0,0,2,"Bulbi"]},{"code":401,"indent":1,"parameters":["Et moi mamie ?"]},{"code":101,"indent":1,"parameters":["1-8",2,0,2,"Florinette"]},{"code":401,"indent":1,"parameters":["C'est vraiment quelque chose d'exceptionnel"]},{"code":401,"indent":1,"parameters":["que \\N[12] ait débloqué sa puissance "]},{"code":401,"indent":1,"parameters":["personnelle aussi jeune, mais ne t'en fais pas "]},{"code":401,"indent":1,"parameters":["mon petit bulbi, mon sang coule dans tes veines"]},{"code":101,"indent":1,"parameters":["1-8",2,0,2,"Florinette"]},{"code":401,"indent":1,"parameters":["toi aussi tu finiras par y accèder, mais plus "]},{"code":401,"indent":1,"parameters":["tard"]},{"code":101,"indent":1,"parameters":["1-8",0,0,2,"Bulbi"]},{"code":401,"indent":1,"parameters":["Trop cool ! T'as entendu \\N[12] ?! Moi aussi"]},{"code":401,"indent":1,"parameters":["je vais devenir aussi fort que toi héhéhé"]},{"code":101,"indent":1,"parameters":["1-8",2,0,2,""]},{"code":401,"indent":1,"parameters":["Si ça ne vous dérange pas, je vais aller faire"]},{"code":401,"indent":1,"parameters":["une petite sieste."]},{"code":121,"indent":1,"parameters":[97,97,1]},{"code":213,"indent":1,"parameters":[7,10,true]},{"code":0,"indent":1,"parameters":[]},{"code":411,"indent":0,"parameters":[]},{"code":213,"indent":1,"parameters":[7,10,true]},{"code":0,"indent":1,"parameters":[]},{"code":412,"indent":0,"parameters":[]},{"code":0,"indent":0,"parameters":[]}],"moveFrequency":3,"moveRoute":{"list":[{"code":0,"parameters":[]}],"repeat":true,"skippable":false,"wait":false},"moveSpeed":3,"moveType":0,"priorityType":1,"stepAnime":false,"through":false,"trigger":0,"walkAnime":true},{"conditions":{"actorId":1,"actorValid":false,"itemId":1,"itemValid":false,"selfSwitchCh":"B","selfSwitchValid":false,"switch1Id":78,"switch1Valid":true,"switch2Id":1,"switch2Valid":false,"variableId":1,"variableValid":false,"variableValue":0},"directionFix":false,"image":{"tileId":0,"characterName":"","direction":4,"pattern":0,"characterIndex":4},"list":[{"code":0,"indent":0,"parameters":[]}],"moveFrequency":3,"moveRoute":{"list":[{"code":0,"parameters":[]}],"repeat":true,"skippable":false,"wait":false},"moveSpeed":3,"moveType":0,"priorityType":0,"stepAnime":false,"through":false,"trigger":0,"walkAnime":false}],"x":4,"y":3},
{"id":8,"name":"post scout cutscene","note":"","pages":[{"conditions":{"actorId":1,"actorValid":false,"itemId":1,"itemValid":false,"selfSwitchCh":"A","selfSwitchValid":false,"switch1Id":74,"switch1Valid":true,"switch2Id":1,"switch2Valid":false,"variableId":1,"variableValid":false,"variableValue":0},"directionFix":false,"image":{"characterIndex":0,"characterName":"","direction":2,"pattern":0,"tileId":0},"list":[{"code":101,"indent":0,"parameters":["1-8",2,0,2,"Florinette"]},{"code":401,"indent":0,"parameters":["\\P[1], je voulais te remercier d'avoir défendu"]},{"code":401,"indent":0,"parameters":["notre village aux côtés de Bulbi."]},{"code":101,"indent":0,"parameters":["1-8",0,0,2,"Bulbi"]},{"code":401,"indent":0,"parameters":["Mamie, \\P[1] est super fort ! Il ne s'était "]},{"code":401,"indent":0,"parameters":["jamais encore battu et il a super assuré !"]},{"code":250,"indent":0,"parameters":[{"name":"_pixel-sound-effect-5-103221","volume":90,"pitch":150,"pan":0}]},{"code":213,"indent":0,"parameters":[-1,6,true]},{"code":101,"indent":0,"parameters":["nyxoro_face",0,0,2,"\\P[1]"]},{"code":401,"indent":0,"parameters":["Je n'ai fait qu'appliquer tes conseils bulbi, "]},{"code":401,"indent":0,"parameters":["j'ai chargé avec mon corps, foncé avec mes "]},{"code":401,"indent":0,"parameters":["cornes et griffé avec mes griffes."]},{"code":101,"indent":0,"parameters":["1-8",2,0,2,"Florinette"]},{"code":401,"indent":0,"parameters":["À ce sujet, nous n'avions pas terminé notre "]},{"code":401,"indent":0,"parameters":["discussion de tout à l'heure..."]},{"code":213,"indent":0,"parameters":[7,8,true]},{"code":101,"indent":0,"parameters":["1-8",2,0,2,"Florinette"]},{"code":401,"indent":0,"parameters":["\\P[1], la dernière fois que j'ai croisé un "]},{"code":401,"indent":0,"parameters":["pokémon comme toi, je sortais à peine de l'oeuf"]},{"code":401,"indent":0,"parameters":["et je n'étais pas plus vieille que notre cher "]},{"code":401,"indent":0,"parameters":["Bulbi ici présent."]},{"code":101,"indent":0,"parameters":["nyxoro_face",0,0,2,"\\P[1]"]},{"code":401,"indent":0,"parameters":["Un pokémon comme moi ?"]},{"code":101,"indent":0,"parameters":["1-8",2,0,2,"Florinette"]},{"code":401,"indent":0,"parameters":["Oui."]},{"code":243,"indent":0,"parameters":[]},{"code":242,"indent":0,"parameters":[1]},{"code":250,"indent":0,"parameters":[{"name":"06-Obtained-a-Key-Item_","volume":90,"pitch":100,"pan":0}]},{"code":101,"indent":0,"parameters":["1-8",2,0,2,"Florinette"]},{"code":401,"indent":0,"parameters":["Tu es un \\C[1]Nyxoro\\C[0] \\P[1]."]},{"code":321,"indent":0,"parameters":[12,17,true]},{"code":230,"indent":0,"parameters":[60]},{"code":244,"indent":0,"parameters":[]},{"code":213,"indent":0,"parameters":[-1,1,false]},{"code":213,"indent":0,"parameters":[3,1,false]},{"code":205,"indent":0,"parameters":[-1,{"list":[{"code":44,"parameters":[{"name":"_pixel-jump-319167","volume":90,"pitch":100,"pan":0}],"indent":null},{"code":14,"parameters":[0,0],"indent":null},{"code":44,"parameters":[{"name":"_pixel-jump-319167","volume":90,"pitch":100,"pan":0}],"indent":null},{"code":14,"parameters":[0,0],"indent":null},{"code":0}],"repeat":false,"skippable":false,"wait":false}]},{"code":505,"indent":0,"parameters":[{"code":44,"parameters":[{"name":"_pixel-jump-319167","volume":90,"pitch":100,"pan":0}],"indent":null}]},{"code":505,"indent":0,"parameters":[{"code":14,"parameters":[0,0],"indent":null}]},{"code":505,"indent":0,"parameters":[{"code":44,"parameters":[{"name":"_pixel-jump-319167","volume":90,"pitch":100,"pan":0}],"indent":null}]},{"code":505,"indent":0,"parameters":[{"code":14,"parameters":[0,0],"indent":null}]},{"code":205,"indent":0,"parameters":[3,{"list":[{"code":44,"parameters":[{"name":"_pixel-jump-319167","volume":90,"pitch":100,"pan":0}],"indent":null},{"code":14,"parameters":[0,0],"indent":null},{"code":44,"parameters":[{"name":"_pixel-jump-319167","volume":90,"pitch":100,"pan":0}],"indent":null},{"code":14,"parameters":[0,0],"indent":null},{"code":0}],"repeat":false,"skippable":false,"wait":true}]},{"code":505,"indent":0,"parameters":[{"code":44,"parameters":[{"name":"_pixel-jump-319167","volume":90,"pitch":100,"pan":0}],"indent":null}]},{"code":505,"indent":0,"parameters":[{"code":14,"parameters":[0,0],"indent":null}]},{"code":505,"indent":0,"parameters":[{"code":44,"parameters":[{"name":"_pixel-jump-319167","volume":90,"pitch":100,"pan":0}],"indent":null}]},{"code":505,"indent":0,"parameters":[{"code":14,"parameters":[0,0],"indent":null}]},{"code":101,"indent":0,"parameters":["",0,1,1,""]},{"code":401,"indent":0,"parameters":[""]},{"code":401,"indent":0,"parameters":["                   UN \\C[1]NYXORO\\C[0] !"]},{"code":101,"indent":0,"parameters":["1-8",0,0,2,"Bulbi"]},{"code":401,"indent":0,"parameters":[""]},{"code":401,"indent":0,"parameters":["C'est trop cool !"]},{"code":230,"indent":0,"parameters":[60]},{"code":250,"indent":0,"parameters":[{"name":"_pixel-sound-effect-5-103221","volume":90,"pitch":150,"pan":0}]},{"code":213,"indent":0,"parameters":[3,2,true]},{"code":101,"indent":0,"parameters":["1-8",0,0,2,"Bulbi"]},{"code":401,"indent":0,"parameters":[""]},{"code":401,"indent":0,"parameters":["Pourquoi \\P[1] est le premier Nyxoro que je "]},{"code":401,"indent":0,"parameters":["croise ?"]},{"code":213,"indent":0,"parameters":[7,8,true]},{"code":101,"indent":0,"parameters":["1-8",2,0,2,"Florinette"]},{"code":401,"indent":0,"parameters":["Car c'est une race de pokémon éteinte depuis"]},{"code":401,"indent":0,"parameters":["plusieurs centaines d'années..."]},{"code":101,"indent":0,"parameters":["1-8",0,0,2,"Bulbi"]},{"code":401,"indent":0,"parameters":[""]},{"code":401,"indent":0,"parameters":["Mais attend... ça veut dire que..."]},{"code":213,"indent":0,"parameters":[3,1,false]},{"code":205,"indent":0,"parameters":[3,{"list":[{"code":44,"parameters":[{"name":"_pixel-jump-319167","volume":90,"pitch":100,"pan":0}],"indent":null},{"code":14,"parameters":[0,0],"indent":null},{"code":44,"parameters":[{"name":"_pixel-jump-319167","volume":90,"pitch":100,"pan":0}],"indent":null},{"code":14,"parameters":[0,0],"indent":null},{"code":0}],"repeat":false,"skippable":false,"wait":true}]},{"code":505,"indent":0,"parameters":[{"code":44,"parameters":[{"name":"_pixel-jump-319167","volume":90,"pitch":100,"pan":0}],"indent":null}]},{"code":505,"indent":0,"parameters":[{"code":14,"parameters":[0,0],"indent":null}]},{"code":505,"indent":0,"parameters":[{"code":44,"parameters":[{"name":"_pixel-jump-319167","volume":90,"pitch":100,"pan":0}],"indent":null}]},{"code":505,"indent":0,"parameters":[{"code":14,"parameters":[0,0],"indent":null}]},{"code":101,"indent":0,"parameters":["1-8",0,0,2,"Bulbi"]},{"code":401,"indent":0,"parameters":[""]},{"code":401,"indent":0,"parameters":["MAMIE ?! MAIS TU AS QUEL ÂGE ?"]},{"code":101,"indent":0,"parameters":["1-8",2,0,2,"Florinette"]},{"code":401,"indent":0,"parameters":[""]},{"code":401,"indent":0,"parameters":["AHAHAHAH !"]},{"code":101,"indent":0,"parameters":["1-8",2,0,2,"Florinette"]},{"code":401,"indent":0,"parameters":["C'est donc ce qui te préoccupe le plus ?"]},{"code":101,"indent":0,"parameters":["1-8",2,0,2,"Florinette"]},{"code":401,"indent":0,"parameters":["Passons. \\P[1] voilà où s'achève mon savoir"]},{"code":401,"indent":0,"parameters":["te concernant. Je pensais que tous les "]},{"code":401,"indent":0,"parameters":["Nyxoro avaient disparus, mais grâce à toi, "]},{"code":401,"indent":0,"parameters":["nous savons que ce n'est pas le cas."]},{"code":101,"indent":0,"parameters":["1-8",2,0,2,"Florinette"]},{"code":401,"indent":0,"parameters":["Tu n'as plus le choix, tu dois partir à "]},{"code":401,"indent":0,"parameters":["l'aventure et trouver tes semblables pour"]},{"code":401,"indent":0,"parameters":["apprendre d'où tu viens et qui tu es vraiment."]},{"code":213,"indent":0,"parameters":[3,1,false]},{"code":205,"indent":0,"parameters":[3,{"list":[{"code":44,"parameters":[{"name":"_pixel-jump-319167","volume":90,"pitch":100,"pan":0}],"indent":null},{"code":14,"parameters":[0,0],"indent":null},{"code":44,"parameters":[{"name":"_pixel-jump-319167","volume":90,"pitch":100,"pan":0}],"indent":null},{"code":14,"parameters":[0,0],"indent":null},{"code":0}],"repeat":false,"skippable":false,"wait":true}]},{"code":505,"indent":0,"parameters":[{"code":44,"parameters":[{"name":"_pixel-jump-319167","volume":90,"pitch":100,"pan":0}],"indent":null}]},{"code":505,"indent":0,"parameters":[{"code":14,"parameters":[0,0],"indent":null}]},{"code":505,"indent":0,"parameters":[{"code":44,"parameters":[{"name":"_pixel-jump-319167","volume":90,"pitch":100,"pan":0}],"indent":null}]},{"code":505,"indent":0,"parameters":[{"code":14,"parameters":[0,0],"indent":null}]},{"code":101,"indent":0,"parameters":["1-8",0,0,2,"Bulbi"]},{"code":401,"indent":0,"parameters":["Si \\P[1] s'en va je pars aussi !"]},{"code":101,"indent":0,"parameters":["1-8",2,0,2,"Florinette"]},{"code":401,"indent":0,"parameters":["Soit."]},{"code":101,"indent":0,"parameters":["1-8",2,0,2,"Florinette"]},{"code":401,"indent":0,"parameters":["Qu'il en soit ainsi."]},{"code":101,"indent":0,"parameters":["1-8",0,0,2,"Bulbi"]},{"code":401,"indent":0,"parameters":["Et si le village se fait à nouveau attaquer ?"]},{"code":101,"indent":0,"parameters":["1-8",2,0,2,"Florinette"]},{"code":401,"indent":0,"parameters":["Ne t'inquiètes pas mon petit Bulbi, mamie est"]},{"code":401,"indent":0,"parameters":["là pour le protéger. Et même si cela ne devait"]},{"code":401,"indent":0,"parameters":["pas suffire, cela fait maintenant plusieurs "]},{"code":401,"indent":0,"parameters":["semaines que \\C[18]Cizayox\\C[0] est parti au \\C[17]Mt Grisnox.\\C[0]"]},{"code":101,"indent":0,"parameters":["1-8",2,0,2,"Florinette"]},{"code":401,"indent":0,"parameters":["Il ne devrait plus tarder à rentrer maintenant."]},{"code":401,"indent":0,"parameters":["Et avec lui le village ne court aucun danger."]},{"code":205,"indent":0,"parameters":[3,{"list":[{"code":25,"indent":null},{"code":0}],"repeat":false,"skippable":false,"wait":true}]},{"code":505,"indent":0,"parameters":[{"code":25,"indent":null}]},{"code":101,"indent":0,"parameters":["1-8",0,0,2,"Bulbi"]},{"code":401,"indent":0,"parameters":["T'es prêt à retrouver tes origines \\P[1] ? "]},{"code":401,"indent":0,"parameters":["Alors c'est partiiii !!!"]},{"code":355,"indent":0,"parameters":["$gamePlayer.showFollowers();"]},{"code":655,"indent":0,"parameters":["$gamePlayer.refresh();"]},{"code":121,"indent":0,"parameters":[76,76,0]},{"code":123,"indent":0,"parameters":["A",0]},{"code":0,"indent":0,"parameters":[]}],"moveFrequency":3,"moveRoute":{"list":[{"code":0,"parameters":[]}],"repeat":true,"skippable":false,"wait":false},"moveSpeed":3,"moveType":0,"priorityType":0,"stepAnime":false,"through":false,"trigger":3,"walkAnime":true},{"conditions":{"actorId":1,"actorValid":false,"itemId":1,"itemValid":false,"selfSwitchCh":"A","selfSwitchValid":true,"switch1Id":1,"switch1Valid":false,"switch2Id":1,"switch2Valid":false,"variableId":1,"variableValid":false,"variableValue":0},"directionFix":false,"image":{"characterIndex":0,"characterName":"","direction":2,"pattern":0,"tileId":0},"list":[{"code":0,"indent":0,"parameters":[]}],"moveFrequency":3,"moveRoute":{"list":[{"code":0,"parameters":[]}],"repeat":true,"skippable":false,"wait":false},"moveSpeed":3,"moveType":0,"priorityType":0,"stepAnime":false,"through":false,"trigger":0,"walkAnime":true}],"x":3,"y":0},
{"id":9,"name":"changement de carte","note":"","pages":[{"conditions":{"actorId":1,"actorValid":false,"itemId":1,"itemValid":false,"selfSwitchCh":"A","selfSwitchValid":false,"switch1Id":76,"switch1Valid":true,"switch2Id":1,"switch2Valid":false,"variableId":1,"variableValid":false,"variableValue":0},"directionFix":false,"image":{"characterIndex":0,"characterName":"","direction":2,"pattern":0,"tileId":0},"list":[{"code":122,"indent":0,"parameters":[14,14,0,3,5,-1,0]},{"code":122,"indent":0,"parameters":[15,15,0,3,5,-1,1]},{"code":285,"indent":0,"parameters":[9,6,2,-1,0]},{"code":111,"indent":0,"parameters":[1,9,0,1,0]},{"code":250,"indent":1,"parameters":[{"name":"Switch1","volume":65,"pitch":50,"pan":0}]},{"code":201,"indent":1,"parameters":[0,18,9,10,2,0]},{"code":0,"indent":1,"parameters":[]},{"code":412,"indent":0,"parameters":[]},{"code":0,"indent":0,"parameters":[]}],"moveFrequency":3,"moveRoute":{"list":[{"code":0,"parameters":[]}],"repeat":true,"skippable":false,"wait":false},"moveSpeed":3,"moveType":0,"priorityType":0,"stepAnime":false,"through":false,"trigger":4,"walkAnime":true}],"x":4,"y":0},
null
]
}